_cffi_backend.cpython-38-x86_64-linux-gnu.so
cffi-1.15.1.dist-info/top_level.txt
cffi-1.15.1.dist-info/entry_points.txt
cffi-1.15.1.dist-info/WHEEL
cffi-1.15.1.dist-info/LICENSE
cffi-1.15.1.dist-info/METADATA
cffi-1.15.1.dist-info/RECORD
cffi/vengine_gen.py
cffi/backend_ctypes.py
cffi/cparser.py
cffi/_cffi_errors.h
cffi/api.py
cffi/_embedding.h
cffi/pkgconfig.py
cffi/commontypes.py
cffi/model.py
cffi/_cffi_include.h
cffi/parse_c_type.h
cffi/lock.py
cffi/recompiler.py
cffi/vengine_cpy.py
cffi/ffiplatform.py
cffi/setuptools_ext.py
cffi/cffi_opcode.py
cffi/error.py
cffi/__init__.py
cffi/verifier.py
